rpi_reactive_gpio/__init__.py
rpi_reactive_gpio/buttons.py
rpi_reactive_gpio/leds.py
rpi_reactive_gpio/main.py
rpi_reactive_gpio/pin_manager.py
rpi_reactive_gpio/scene.py
rpi_reactive_gpio-0.1.10.dist-info/LICENSE
rpi_reactive_gpio-0.1.10.dist-info/METADATA
rpi_reactive_gpio-0.1.10.dist-info/WHEEL
rpi_reactive_gpio-0.1.10.dist-info/RECORD
